kicad_auto_lib/Sexp_read_write.py
kicad_auto_lib/__init__.py
kicad_auto_lib/__main__.py
kicad_auto_lib/constants.py
kicad_auto_lib/file_manage.py
kicad_auto_lib/file_monitor.py
kicad_auto_lib/git_manage.py
kicad_auto_lib/kicad_auto_lib.py
kicad_auto_lib/variables.py
kicad_auto_lib-0.0.3.dist-info/entry_points.txt
kicad_auto_lib-0.0.3.dist-info/LICENSE
kicad_auto_lib-0.0.3.dist-info/WHEEL
kicad_auto_lib-0.0.3.dist-info/METADATA
kicad_auto_lib-0.0.3.dist-info/RECORD
