Metadata-Version: 2.3
Name: kicad_auto_lib
Version: 0.0.3
Summary: Fully automated library management in Kicad. Don't open the Manage Symbol/Footprint Libraries ever again.
Author-email: "Charles H. Gayot" <charles@stepupsolutions.dk>
Requires-Python: >=3.8
Classifier: Programming Language :: Python :: 3
Classifier: Operating System :: OS Independent
Classifier: License :: OSI Approved :: GNU Affero General Public License v3
Requires-Dist: watchdog>=6.0.0
Requires-Dist: sexpdata>=1.0.2
Project-URL: Homepage, https://github.com/StepUp-Solutions/kicad_auto_lib
Project-URL: Issues, https://github.com/StepUp-Solutions/kicad_auto_lib/issues
